{
  "all_checks_passed": true,
  "backward_called": false,
  "blocking_reasons": [],
  "checkpoint_loaded": true,
  "checkpoint_path": "checkpoints/crossdocked_fullatom_cond.ckpt",
  "checkpoint_saved": false,
  "checkpoint_sha256": "07f86764bf569aafbc40a9c15fc02de8e2550437dd0f17f657eab3abe66c372c",
  "checkpoint_size_bytes": 17861341,
  "checkpoint_state_dict_key_count": 122,
  "finetune_allowed": false,
  "forbidden_artifacts_created": false,
  "formal_training_allowed": false,
  "forward_smoke_attempted": true,
  "forward_smoke_success": true,
  "incompatible_shape_count": 0,
  "inf_count": 0,
  "load_smoke_status": "checkpoint_compatible_pretrained_load_proven",
  "loaded_parameter_key_count": 122,
  "loaded_parameter_numel_total": 1006560,
  "loss_decrease_required": false,
  "masked_loss_smoke_allowed": false,
  "missing_keys_count": 0,
  "model_class": "LigandPocketDDPM",
  "model_instantiated": true,
  "model_saved": false,
  "model_state_dict_key_count": 122,
  "nan_count": 0,
  "optimizer_created": false,
  "optimizer_step_called": false,
  "original_source_files_modified": false,
  "output_finite": true,
  "output_shape_summary": {
    "output.0": [
      1
    ],
    "output.1.SNR_weight": [],
    "output.1.delta_log_px": [],
    "output.1.eps_hat_lig_h": [],
    "output.1.eps_hat_lig_x": [],
    "output.1.error_t_lig": [],
    "output.1.error_t_pocket": [],
    "output.1.kl_prior": [],
    "output.1.log_pN": [],
    "output.1.loss_0": [],
    "output.1.neg_log_const_0": []
  },
  "pre_load_incompatible_shape_count": 0,
  "pre_load_shape_matched_key_count": 122,
  "pre_load_shape_matched_ratio": 1.0,
  "pretrained_base_integration_proven": true,
  "pretrained_masked_loss_smoke_allowed": true,
  "pretrained_weights_loaded": true,
  "previous_stage": "checkpoint_compatible_instantiation_wrapper_v0",
  "quality_claim_allowed": false,
  "recommended_next_step": "pretrained_masked_loss_smoke_on_checkpoint_compatible_model",
  "requested_device": "cpu",
  "resolved_device": "cpu",
  "stage": "checkpoint_compatible_pretrained_load_smoke_v0",
  "step11d_validated": true,
  "strict_load_attempted": true,
  "strict_load_success": true,
  "trainer_fit_called": false,
  "training_allowed": false,
  "training_step_called": false,
  "unexpected_keys_count": 0
}
